Metadata-Version: 2.1
Name: botcity-aws-sqs-plugin
Version: 0.1.3
Home-page: https://bitbucket.org/botcitydev/bot-aws-sqs-plugin-python.git
Requires-Python: >=3.7
